qiskit_cold_atom/VERSION.txt
qiskit_cold_atom/__init__.py
qiskit_cold_atom/base_circuit_solver.py
qiskit_cold_atom/circuit_tools.py
qiskit_cold_atom/exceptions.py
qiskit_cold_atom/applications/__init__.py
qiskit_cold_atom/applications/fermi_hubbard.py
qiskit_cold_atom/applications/fermionic_evolution_problem.py
qiskit_cold_atom/applications/time_evolution_solver.py
qiskit_cold_atom/fermions/__init__.py
qiskit_cold_atom/fermions/base_fermion_backend.py
qiskit_cold_atom/fermions/fermion_circuit_solver.py
qiskit_cold_atom/fermions/fermion_gate_library.py
qiskit_cold_atom/fermions/fermion_simulator_backend.py
qiskit_cold_atom/fermions/fermionic_basis.py
qiskit_cold_atom/fermions/fermionic_state.py
qiskit_cold_atom/providers/__init__.py
qiskit_cold_atom/providers/cold_atom_job.py
qiskit_cold_atom/providers/cold_atom_provider.py
qiskit_cold_atom/providers/collective_spin_backend.py
qiskit_cold_atom/providers/fermionic_tweezer_backend.py
qiskit_cold_atom/providers/remote_backend.py
qiskit_cold_atom/spins/__init__.py
qiskit_cold_atom/spins/base_spin_backend.py
qiskit_cold_atom/spins/spin_circuit_solver.py
qiskit_cold_atom/spins/spin_simulator_backend.py
qiskit_cold_atom/spins/spins_gate_library.py
qiskit_cold_atom/transpiler/__init__.py
qiskit_cold_atom/transpiler/single_spin_gates.py
qiskit_cold_atom-0.2.1.dist-info/LICENSE
qiskit_cold_atom-0.2.1.dist-info/METADATA
qiskit_cold_atom-0.2.1.dist-info/WHEEL
qiskit_cold_atom-0.2.1.dist-info/top_level.txt
qiskit_cold_atom-0.2.1.dist-info/RECORD
